Metadata-Version: 1.0
Name: neurobit
Version: 1.1
Summary: Neurobit Utilities to score and analyze sleep data using the Z3Score Framework.
Home-page: https://github.com/neurobittechnologies/neurobit
Author: Amiya Patanaik
Author-email: amiya@neurobit.io
License: GPL
Platform: UNKNOWN
